{
  "category_name": "NWN World",
  "category_id": "001",
  "forum_name": "General",
  "forum_id": "000",
  "id": "049",
  "name": "Character Creation.",
  "link": "https://www.tapatalk.com/groups/nwnecbguild/character-creation-t515507.html",
  "author": "NwnwhiteBoy",
  "avatar": "no_avatar.png",
  "replies": "7",
  "views": "888",
  "posts": [
    {
      "author": "NwnwhiteBoy",
      "avatar": "no_avatar.png",
      "timestamp": "8:37 AM - Oct 11, 2011",
      "content": "<div>I was wondering, can you make up a character out side of NWN, on a spreadsheet or something (Like CBC on Excel)? And then import it to be playable? So you don't have to go through the tedious process of being in-game and levelling up.</div>"
    },
    {
      "author": "avado",
      "avatar": "no_avatar.png",
      "timestamp": "4:13 AM - Oct 12, 2011",
      "content": "<div>I create characters on paper.  In fact, I dont even need a game to make them.</div>"
    },
    {
      "author": "Grimnir",
      "avatar": "10235237_1517392314.jpg",
      "timestamp": "5:20 AM - Oct 12, 2011",
      "content": "<div>That's not what he's asking though, but I don't know a way at least, nwnwhiteboy.</div>"
    },
    {
      "author": "NwnwhiteBoy",
      "avatar": "no_avatar.png",
      "timestamp": "6:40 AM - Oct 14, 2011",
      "content": "<div>Okay, sweet would be amazing if there was!! <br/>\n<br/>\nThanks anyways!!</div>"
    },
    {
      "author": "Maximillian Kane",
      "avatar": "10235244_1510287070.jpg",
      "timestamp": "2:03 PM - Oct 15, 2011",
      "content": "<div>It's not as tedious if the server has scripts to give you MAX HP each level in place. otherwise you need to keep rerolling till you attain a max roll.<br/>\n<br/>\nTake it EZ!</div>"
    },
    {
      "author": "KailPendragon",
      "avatar": "10235214_1540245864.jpg",
      "timestamp": "5:26 PM - Oct 15, 2011",
      "content": "<div><blockquote><div><strong>Maximillian Kane wrote:</strong>It's not as tedious if the server has scripts to give you MAX HP each level in place. otherwise you need to keep rerolling till you attain a max roll.<br/>\n<br/>\nTake it EZ!</div></blockquote>There's no need of special scripts, just of turning on the max HP switch BW graciously implemented in 1.69 (which of course is under the player's control in SP).</div>"
    },
    {
      "author": "Maximillian Kane",
      "avatar": "10235244_1510287070.jpg",
      "timestamp": "4:04 PM - Oct 17, 2011",
      "content": "<div><blockquote><div><strong>KailPendragon wrote:</strong><blockquote><div><strong>Maximillian Kane wrote:</strong>It's not as tedious if the server has scripts to give you MAX HP each level in place. otherwise you need to keep rerolling till you attain a max roll.<br/>\n<br/>\nTake it EZ!</div></blockquote>There's no need of special scripts, just of turning on the max HP switch BW graciously implemented in 1.69 (which of course is under the player's control in SP).</div></blockquote>\n\nHow do you do that?</div>"
    },
    {
      "author": "KailPendragon",
      "avatar": "10235214_1540245864.jpg",
      "timestamp": "4:19 PM - Oct 17, 2011",
      "content": "<div><a class=\"postlink\" href=\"http://nwn.wikia.com/wiki/Nwnplayer.ini\" rel=\"noreferrer\" target=\"_blank\">nwnplayer.ini</a><br/>\n<br/>\nSet \"Max Hit Points\" to 1</div>"
    }
  ]
}